pomo/__init__.py
pomo/core.py
pomo/sound.py
pomo/utils.py
pomo-0.10.data/scripts/pomo
pomo-0.10.dist-info/DESCRIPTION.rst
pomo-0.10.dist-info/METADATA
pomo-0.10.dist-info/RECORD
pomo-0.10.dist-info/WHEEL
pomo-0.10.dist-info/metadata.json
pomo-0.10.dist-info/namespace_packages.txt
pomo-0.10.dist-info/top_level.txt
pomo-0.10.dist-info/zip-safe
