Metadata-Version: 2.0
Name: pomo
Version: 0.10
Summary: UNKNOWN
Home-page: UNKNOWN
Author: UNKNOWN
Author-email: UNKNOWN
License: UNKNOWN
Platform: UNKNOWN
Classifier: Development Status :: 3 - Alpha
Classifier: Programming Language :: Python
Requires-Dist: docopt
Requires-Dist: pygame
Requires-Dist: pyyaml
